{
  "$schema": "https://repomix.com/schemas/latest/schema.json",
  "input": {
    "maxFileSize": 52428800
  },
  "output": {
    "filePath": "docs/repomix.md",
    "style": "markdown",
    "parsableStyle": true,
    "fileSummary": false,
    "directoryStructure": true,
    "files": true,
    "removeComments": false,
    "removeEmptyLines": false,
    "compress": false,
    "topFilesLength": 5,
    "showLineNumbers": false,
    "copyToClipboard": true,
    "git": {
      "sortByChanges": true,
      "sortByChangesMaxCommits": 100,
      "includeDiffs": false
    }
  },
  "include": [
    // "README.md",
    "package.json",
    "vite.config.ts",
    "tsconfig.json",
    "tsconfig.node.json",
    "tailwind.config.js",
    "postcss.config.js",
    "index.html",
    // "src"
    "src/components/auth/LoginPage.tsx",
    "src/index.ts",
    "src/components/ui/label.tsx",
    "src/pages/DataDemo/components/DataListView.tsx",
    "src/pages/DataDemo/components/DataCardView.tsx",
    "src/pages/DataDemo/components/DataDetailPanel.tsx",
    "src/pages/Dashboard/hooks/useDashboardAnimations.hook.ts",
    "src/pages/Dashboard/hooks/useDemoContentAnimations.hook.ts",
    "src/pages/Dashboard/DemoContent.tsx",
    "src/pages/Dashboard/index.tsx",
    "src/pages/DataDemo/index.tsx",
    "src/pages/DataDemo/types.ts",
    "src/pages/DataDemo/components/DataToolbar.tsx",
    "src/components/auth/LoginPage.tsx",
    "src/components/effects/AnimatedInput.tsx",
    "src/components/effects/BottomGradient.tsx",
    "src/components/effects/BoxReveal.tsx",
    "src/components/effects/OrbitingCircles.tsx",
    "src/components/effects/Ripple.tsx",
    "src/index.ts",
    "src/hooks/useStaggeredAnimation.motion.ts",
    "src/pages/Dashboard/DemoContent.tsx",
    "src/pages/Dashboard/hooks/useDashboardAnimations.motion.ts",
    "src/pages/Dashboard/index.tsx",
    "src/pages/DataDemo/components/DataCardView.tsx",
    "src/pages/DataDemo/components/DataDetailPanel.tsx",
    "src/pages/DataDemo/components/DataListView.tsx"
  ],
  "ignore": {
    "useGitignore": true,
    "useDefaultPatterns": true,
    "customPatterns": [
      "src/pages/DataDemo/data"
      // "src/features/settings",
      // // "src/pages/Dashboard",
      // "src/pages/ToasterDemo",
      // "src/pages/Notifications",
      // "src/components/ui"
    ]
  },
  "security": {
    "enableSecurityCheck": true
  },
  "tokenCount": {
    "encoding": "o200k_base"
  }
}
